LICENSE
starlit/__init__.py
starlit-0.1.0.dist-info/LICENSE
starlit-0.1.0.dist-info/WHEEL
starlit-0.1.0.dist-info/METADATA
starlit-0.1.0.dist-info/RECORD
